autolgb/__init__.py
autolgb/basic.py
autolgb/dataset.py
autolgb/engine.py
autolgb-0.0.1.dist-info/METADATA
autolgb-0.0.1.dist-info/WHEEL
autolgb-0.0.1.dist-info/RECORD
